README.md
setup.py
ktk/__init__.py
ktk/locker/__init__.py
ktk/locker/locker_test.py
ktk_python.egg-info/PKG-INFO
ktk_python.egg-info/SOURCES.txt
ktk_python.egg-info/dependency_links.txt
ktk_python.egg-info/top_level.txt